Metadata-Version: 2.0
Name: odoo8-addon-l10n-be-eco-tax
Version: 8.0.1.0.0
Summary: Data module to support BEBAT and RECUPEL taxes
Home-page: http://www.acsone.eu
Author: ACSONE SA/NV,Odoo Community Association (OCA)
Author-email: support@odoo-community.org
License: AGPL-3
Platform: UNKNOWN
Requires-Dist: odoo (<9.0a,>=8.0a)
Classifier: Programming Language :: Python :: 2.7
Classifier: Framework :: Odoo
Classifier: License :: OSI Approved :: GNU Affero General Public License v3
